pybatcher/__init__.py
pybatcher/batch.py
pybatcher/batcher.py
pybatcher/exceptions.py
pybatcher/utils.py
pybatcher-1.0.1.dist-info/licenses/LICENCE
pybatcher-1.0.1.dist-info/METADATA
pybatcher-1.0.1.dist-info/WHEEL
pybatcher-1.0.1.dist-info/top_level.txt
pybatcher-1.0.1.dist-info/RECORD
