Metadata-Version: 2.4
Name: pybatcher
Version: 1.0.1
Summary: A library for managing batch processing in Python.
Home-page: https://git.jimw.fr/pybatcher
Author: Jimw
Author-email: Jimw <jimmy.c@jimw.fr>
License: MIT
Project-URL: Homepage, https://git.jimw.fr/pybatcher
Project-URL: Repository, https://git.jimw.fr/pybatcher
Classifier: Programming Language :: Python :: 3
Classifier: Operating System :: OS Independent
Requires-Python: >=3.6
License-File: LICENCE
Dynamic: author
Dynamic: home-page
Dynamic: license-file
Dynamic: requires-python
